{
  "$schema": "../../changelogSchema.json",
  "content": [
    {
      "date": "xx.10.23",
      "version": "3.1.1",
      "changelog": [
        {
          "type": "patch",
          "changes": ["Updated internal dependencies."]
        }
      ]
    },
    {
      "date": "24.08.23",
      "version": "3.1.0",
      "changelog": [
        {
          "type": "new_feature",
          "changes": ["Dark theme support."]
        }
      ]
    },
    {
      "date": "28.06.23",
      "version": "3.0.2",
      "changelog": [
        {
          "type": "patch",
          "changes": ["The component prop interface now correctly accepts all native properties in React."]
        }
      ]
    },
    {
      "date": "15.06.23",
      "version": "3.0.1 ",
      "changelog": [
        {
          "type": "patch",
          "changes": ["Updated internal dependencies."]
        }
      ]
    },
    {
      "date": "05.05.23",
      "version": "3.0.0",
      "changelog": [
        {
          "type": "breaking_changes",
          "changes": [
            "<code>title</code> prop has been deprecated in favor of <code>heading</code> so that all components follow the same convention.",
            "<code>type='title'</code> has been deprecated in favor of <code>type='heading'</code> to make the prop consistent with the new <code>heading</code> prop."
          ]
        }
      ]
    },
    {
      "date": "03.05.23",
      "version": "2.0.1",
      "changelog": [
        {
          "type": "patch",
          "changes": ["Updated internal dependencies."]
        }
      ]
    },
    {
      "date": "27.02.23",
      "version": "2.0.0",
      "changelog": [
        {
          "type": "breaking_changes",
          "changes": ["Removed the <code>isInverted</code> prop in favour of better dark mode support."]
        },
        {
          "type": "new_feature",
          "changes": ["Added support for dark theme."]
        }
      ]
    },
    {
      "date": "20.12.22",
      "version": "1.4.4",
      "changelog": [
        {
          "type": "patch",
          "changes": ["Add missing dependency."]
        }
      ]
    },
    {
      "date": "29.11.22",
      "version": "1.4.3",
      "changelog": [
        {
          "type": "patch",
          "changes": ["The component config has been moved into each component."]
        }
      ]
    },
    {
      "date": "21.11.22",
      "version": "1.4.2",
      "changelog": [
        {
          "type": "patch",
          "changes": ["Added support for React 18."]
        }
      ]
    },
    {
      "date": "02.11.22",
      "version": "1.4.1",
      "changelog": [
        {
          "type": "patch",
          "changes": [
            "Use <span class=\"code-text\">@elvia/elvis-component-wrapper@^3.0.0</span>.",
            "Now using the <span class=\"code-text\">@elvia/elvis-typography</span> for typography for the title type divider."
          ]
        }
      ]
    },
    {
      "date": "16.08.22",
      "version": "1.4.0",
      "changelog": [
        {
          "type": "new_feature",
          "changes": [
            "Reworked the way the component is declared as a module, and how types are exported for React. "
          ]
        }
      ]
    },
    {
      "date": "03.05.22",
      "version": "1.3.0 ",
      "changelog": [
        {
          "type": "new_feature",
          "changes": ["Added support for native events in React. "]
        }
      ]
    },
    {
      "date": "04.04.22",
      "version": "1.2.7 ",
      "changelog": [
        {
          "type": "patch",
          "changes": ["Added separator role for the dividers, for better accessibility."]
        }
      ]
    },
    {
      "date": "23.03.22",
      "version": "1.2.6 ",
      "changelog": [
        {
          "type": "patch",
          "changes": [
            "Fixed an issue causing problems for events in non-React environments for props with falsy values. This  update bumps the dependency on @elvia/elvis-component-wrapper."
          ]
        }
      ]
    },
    {
      "date": "09.03.22",
      "version": "1.2.5 ",
      "changelog": [
        {
          "type": "patch",
          "changes": ["Fixed peerDependencies."]
        }
      ]
    },
    {
      "date": "04.03.22",
      "version": "1.2.4 ",
      "changelog": [
        {
          "type": "patch",
          "changes": ["Now using correct type for webcomponent wrapper for better internal IntelliSense."]
        }
      ]
    },
    {
      "date": "28.02.22",
      "version": "1.2.3 ",
      "changelog": [
        {
          "type": "bug_fix",
          "changes": ["Web components inside web components rerender bug fix."]
        }
      ]
    },
    {
      "date": "18.02.22",
      "version": "1.2.1 ",
      "changelog": [
        {
          "type": "bug_fix",
          "changes": ["Added height: 100% to wrapper to fix vertical divider"]
        }
      ]
    },
    {
      "date": "07.02.22",
      "version": "1.2.0 ",
      "changelog": [
        {
          "type": "new_feature",
          "changes": ["Added inlineStyle and className props"]
        }
      ]
    },
    {
      "date": "14.01.22",
      "version": "1.1.7 ",
      "changelog": [
        {
          "type": "patch",
          "changes": ["Refactoring"]
        }
      ]
    },
    {
      "date": "07.01.22",
      "version": "1.1.6 ",
      "changelog": [
        {
          "type": "patch",
          "changes": ["Updated tokens declarations"]
        }
      ]
    },
    {
      "date": "16.12.21",
      "version": "1.1.5 ",
      "changelog": [
        {
          "type": "patch",
          "changes": ["Fix for slotting"]
        }
      ]
    },
    {
      "date": "03.12.21",
      "version": "1.1.3 ",
      "changelog": [
        {
          "type": "patch",
          "changes": ["Added unit tests for divider"]
        }
      ]
    },
    {
      "date": "30.11.21",
      "version": "1.1.2 ",
      "changelog": [
        {
          "type": "patch",
          "changes": ["Now using elvis-colors package for colors."]
        }
      ]
    },
    {
      "date": "30.11.21",
      "version": "1.1.1 ",
      "changelog": [
        {
          "type": "patch",
          "changes": ["Web component wrapper fix"]
        }
      ]
    },
    {
      "date": "17.11.21",
      "version": "1.1.0 ",
      "changelog": [
        {
          "type": "new_feature",
          "changes": ["Added vertical divider"]
        }
      ]
    },
    {
      "date": "07.10.21",
      "version": "1.0.5 ",
      "changelog": [
        {
          "type": "patch",
          "changes": ["Updated inverted divider color from grey-80 to grey-90."]
        }
      ]
    },
    {
      "date": "22.09.21",
      "version": "1.0.4 ",
      "changelog": [
        {
          "type": "bug_fix",
          "changes": ["Fix for bug that made title divider not display titles correctly."]
        }
      ]
    },
    {
      "date": "13.11.20",
      "version": "1.0.0",
      "changelog": [
        {
          "type": "new_feature",
          "changes": ["First version of the divider."]
        }
      ]
    }
  ]
}
